__init__.py
core.py
g4f_utils-0.1.0.dist-info/METADATA
g4f_utils-0.1.0.dist-info/WHEEL
g4f_utils-0.1.0.dist-info/top_level.txt
g4f_utils-0.1.0.dist-info/RECORD
