Metadata-Version: 2.4
Name: g4f-utils
Version: 0.1.0
Requires-Python: >=3.7
Requires-Dist: g4f
